MANIFEST.in
distribute_setup.py
setup.cfg
setup.py
gae_console/__init__.py
gae_console/console.html
gae_console/include.yaml
gae_console.egg-info/PKG-INFO
gae_console.egg-info/SOURCES.txt
gae_console.egg-info/dependency_links.txt
gae_console.egg-info/top_level.txt