Metadata-Version: 1.0
Name: gae-console
Version: 0.0.1
Summary: Powerfull Interactive Console for App Engine applications
Home-page: https://github.com/sadovnychyi/gae-console
Author: Dmitry Sadovnychyi
Author-email: gae-console@dmit.ro
License: Apache License 2.0
Keywords: google app engine,gae,appengine,console,terminal
Platform: UNKNOWN
